processador_de_Imagens/__init__.py
processador_de_Imagens/processando/__init__.py
processador_de_Imagens/processando/combinacao.py
processador_de_Imagens/processando/transformacao.py
processador_de_Imagens/util/__init__.py
processador_de_Imagens/util/io.py
processador_de_Imagens/util/plot.py
Image_Processing_Packeg-0.0.1.dist-info/METADATA
Image_Processing_Packeg-0.0.1.dist-info/WHEEL
Image_Processing_Packeg-0.0.1.dist-info/top_level.txt
Image_Processing_Packeg-0.0.1.dist-info/RECORD
