Metadata-Version: 2.1
Name: Image-Processing-Packeg
Version: 0.0.1
Summary: Projeto de teste do bootcamp-Dio
Home-page: https://github.com/gacavalc
Author: Gacavalc
Author-email: 
License: UNKNOWN
Platform: UNKNOWN
Requires-Python: >=3.8
Requires-Dist: matplotlib
Requires-Dist: numpy
Requires-Dist: scikit-image (>=0.16.1)
